<?xml version='1.0' encoding='UTF-8'?>
<!DOCTYPE appendix PUBLIC "-//OASIS//DTD DocBook XML V4.4//EN"
  "http://www.oasis-open.org/docbook/xml/4.4/docbookx.dtd">


<!-- $Id: credits.xml,v 1.14 2011-12-05 10:55:46 mg Exp $ -->
<appendix id="credits">
<title>Благодарности</title>

<para>
OTRS является проектом с открытым кодом и, мы хотим поблагодарить многих
людей за их помощь и поддержку. Конечно же следующий список далеко неполный
и мы приносим свои извенения за это! Просто напишите нам, если не наши себя
в этом списке.
</para>

<para>
Следующие люди внесли особый вклад в поект и являются его активными
сторонниками:
</para>

<para>
<itemizedlist>
  <listitem>
    <para>
    Robert Kehl, создавший Win32-инсталлятор для релиза 1.x. Больше тебе
спасибо, Robert!
    </para>
  </listitem>
  <listitem>
    <para>
    Torsten Werner, который поддерживаетм Debian-installer для OTRS. Спасибо
большое, Torsten, теперь OTRS также доступен для Debian-сообщества.
    </para>
  </listitem>
  <listitem>
    <para>
    Nils Jeppe (зеркало Гамбург, Германия), Bryan Fullerton (зеркало Торонто,
Канада), Eberhard Mönkeberg (зеркало Геттинген, Германия), Timo Dreger
(зеркало Дюссельдорф, Германия) и Netmonic (зеркало Вена, Австрия), которые
поддерживают зеркальное копии нашего ftp-сервера. Большое спасибо, благодаря
вашей помощи всегда есть возможность быстро скачать OTRS!
    </para>
  </listitem>
  <listitem>
    <para>
    Anja Schneider, которая помогает с переводом этого руководства и коррекции и
пересмотр немецких текстов. Большое спасибо за вашу помощь и терпение, Anja!
    </para>
  </listitem>
  <listitem>
    <para>
    Через списки рассылки OTRS мы получаем множество идей, советов по
усовершенствованию системы, обновления и исправления. Также здесь доступна
большая поддержка для всех пользователй . Большое спасибо всем людям,
которые участвуют в наших списках рассылки за вашу активную помощь!
    </para>
  </listitem>
</itemizedlist>
</para>

<para>
Также мы хотели бы поблагодарить следующих людей:
</para>

<para>
<itemizedlist>
  <listitem>
    <para>
    Martin Scherbaum
    </para>
  </listitem>
  <listitem>
    <para>
    Carsten Gross
    </para>
  </listitem>
  <listitem>
    <para>
    Harald Müller
    </para>
  </listitem>
  <listitem>
    <para>
    Stefan Schmidt
    </para>
  </listitem>
  <listitem>
    <para>
    Milisav Radmanic
    </para>
  </listitem>
  <listitem>
    <para>
    Uli Hecht
    </para>
  </listitem>
  <listitem>
    <para>
    Norman Walsh
    </para>
  </listitem>
  <listitem>
    <para>
    Heiko Baumann
    </para>
  </listitem>
  <listitem>
    <para>
    Atif Ghaffar
    </para>
  </listitem>
  <listitem>
    <para>
    Pablo Ruiz Garcia
    </para>
  </listitem>
  <listitem>
    <para>
    Dan Rau
    </para>
  </listitem>
  <listitem>
    <para>
    Christoph Kaulich
    </para>
  </listitem>
  <listitem>
    <para>
    Mark Jackson
    </para>
  </listitem>
  <listitem>
    <para>
    Diane Shieh
    </para>
  </listitem>
  <listitem>
    <para>
    Bernard Choppy
    </para>
  </listitem>
  <listitem>
    <para>
    Carl Bailey
    </para>
  </listitem>
  <listitem>
    <para>
    Phil Davis
    </para>
  </listitem>
  <listitem>
    <para>
    Edwin D. Vinas
    </para>
  </listitem>
  <listitem>
    <para>
    Lars Müller
    </para>
  </listitem>
  <listitem>
    <para>
    Vladimir Gerdjikov
    </para>
  </listitem>
  <listitem>
    <para>
    Fred van Dijk
    </para>
  </listitem>
  <listitem>
    <para>
    Sebastien Guilbaud
    </para>
  </listitem>
  <listitem>
    <para>
    Wiktor Wodecki
    </para>
  </listitem>
  <listitem>
    <para>
    Arnold Ligtvoet
    </para>
  </listitem>
  <listitem>
    <para>
    Antti Kämäräinen
    </para>
  </listitem>
  <listitem>
    <para>
    Nicolas Goralski
    </para>
  </listitem>
  <listitem>
    <para>
    Gilberto Cezar de Almeida
    </para>
  </listitem>
  <listitem>
    <para>
    Jorge Becerra
    </para>
  </listitem>
  <listitem>
    <para>
    Eddie Urenda
    </para>
  </listitem>
  <listitem>
    <para>
    Stella Power
    </para>
  </listitem>
  <listitem>
    <para>
    Andreas Haase
    </para>
  </listitem>
  <listitem>
    <para>
    Reiner Keller
    </para>
  </listitem>
  <listitem>
    <para>
    Covert Jake
    </para>
  </listitem>
  <listitem>
    <para>
    Moshe Leibovitch
    </para>
  </listitem>
  <listitem>
    <para>
    Bjärn Jacke
    </para>
  </listitem>
  <listitem>
    <para>
    Remo Catelotti
    </para>
  </listitem>
  <listitem>
    <para>
    Alfons Obermeyer
    </para>
  </listitem>
  <listitem>
    <para>
    Michael Rech
    </para>
  </listitem>
  <listitem>
    <para>
    Danie Theron
    </para>
  </listitem>
  <listitem>
    <para>
    Richard Paradies
    </para>
  </listitem>
  <listitem>
    <para>
    Art Powell
    </para>
  </listitem>
</itemizedlist>
</para>

</appendix>